pathnav/__init__.py
pathnav/errors.py
pathnav/pathnav.py
pathnav-1.2.7.dist-info/LICENSE
pathnav-1.2.7.dist-info/LICENSE.txt
pathnav-1.2.7.dist-info/METADATA
pathnav-1.2.7.dist-info/WHEEL
pathnav-1.2.7.dist-info/top_level.txt
pathnav-1.2.7.dist-info/RECORD
